MANIFEST.in
README.md
setup.cfg
setup.py
CRTK/Function-Signature.csv
CRTK/__init__.py
CRTK/contract.py
CRTK/creationcontract.py
CRTK/mapping.py
CRTK/runtimecontract.py
CRTK/utilities.py
CRTK.egg-info/PKG-INFO
CRTK.egg-info/SOURCES.txt
CRTK.egg-info/dependency_links.txt
CRTK.egg-info/requires.txt
CRTK.egg-info/top_level.txt