Metadata-Version: 2.1
Name: CRTK
Version: 0.0.23
Summary: Smart Contract Reverse Engineering Toolkits
Home-page: https://github.com/Yzstr/CRTK
Author: Hao-Nan Zhu
Author-email: hao-nan.zhu@outlook.com
License: MIT
Platform: UNKNOWN
Classifier: Programming Language :: Python :: 3
Classifier: License :: OSI Approved :: MIT License
Classifier: Operating System :: OS Independent
